Workbook

Sheet 0. Instrucciones
B2: CHECKLIST DE CARACTERIZACIÓN Y CALIFICACIÓN DE RIESGOS
B3: Centro de Distribución (CEDI) / Bodega logística
B4: Metodología basada en ISO 31000 (gestión del riesgo), ISO 45001, EN 15635 (estanterías), NFPA (incendio) e ISO 22301 (continuidad).
A6: ¿PARA QUÉ SIRVE ESTE ARCHIVO?
B7: Permite (1) caracterizar el centro de distribución, (2) identificar y calificar sus riesgos, (3) definir cada cuánto se revisa cada riesgo según su criticidad y (4) hacer seguimiento a las acciones.
B8: La caracterización es el paso previo obligatorio: el mismo riesgo (por ejemplo, sismo o carga de fuego) NO tiene la misma calificación en un CEDI de 5.000 m² con estantería selectiva de 6 m que en uno de 40.000 m² con racks de 12 m en zona sísmica alta.
A10: CÓMO USARLO — 7 PASOS
B11: Paso | C11: Qué hacer | D11: Hoja
B12: 1. Caracterizar | C12: Diligencie la ficha del CEDI: tamaño, altura, sistema de almacenamiento, volumen y tipo de producto, muelles, equipos, entorno natural y del vecindario, sistemas de protección y gestión. Cada variable es un modificador del riesgo. | D12: 1. Caracterización CEDI
B13: 2. Depurar el alcance | C13: Recorra la matriz y marque como 'N.A.' los riesgos que no apliquen (por ejemplo, cadena de frío si no maneja refrigerados). No borre filas: deje la evidencia de por qué no aplica. | D13: 2. Matriz de Riesgos
B14: 3. Calificar | C14: Ajuste Probabilidad (1-5) e Impacto (1-5) de cada riesgo con base en la caracterización, el histórico de eventos y la efectividad real de los controles. Los valores vienen precargados como punto de partida del experto; deben validarse en sitio. | D14: 2. Matriz de Riesgos
B15: 4. Verificar en campo | C15: Recorra el CEDI con la columna 'Qué verificar' y registre Cumple / Parcial / No, el hallazgo y la evidencia. Es el checklist propiamente dicho. | D15: 2. Matriz de Riesgos
B16: 5. Definir frecuencias | C16: La frecuencia mínima de revisión se calcula automáticamente según el nivel de riesgo. Compárela con la 'Frecuencia técnica recomendada' (norma o fabricante) y adopte SIEMPRE la más exigente de las dos. | D16: 4. Plan de Inspección
B17: 6. Actuar | C17: Todo hallazgo 'No' o 'Parcial' pasa al plan de acción con responsable, fecha y verificación de eficacia. Los plazos máximos dependen del nivel de riesgo. | D17: 5. Plan de Acción
B18: 7. Monitorear | C18: Revise el tablero, cierre acciones y reevalúe. Además de la periodicidad programada, hay disparadores que obligan a revisar de inmediato (sismo, incendio, accidente grave, cambio de layout o de portafolio). | D18: 6. Tablero
A20: REGLA DE ORO PARA LA FRECUENCIA DE REVISIÓN
B21: Nivel de riesgo (P × I) | C21: Frecuencia mínima de verificación en campo | D21: Reevaluación formal / plazo de acción
B22: Extremo (20 - 25) | C22: Verificación diaria o por turno + inspección formal semanal. Riesgo no aceptable: se interviene o se detiene la operación en ese frente. | D22: Reevaluar mensualmente · Plan de acción ≤ 15 días · Lo acepta la Gerencia
B23: Alto (12 - 16) | C23: Verificación semanal + inspección formal mensual. | D23: Reevaluar trimestralmente · Plan de acción ≤ 30 días · Lo acepta el Jefe de CEDI con visto bueno de HSE
B24: Medio (6 - 10) | C24: Inspección mensual (elementos operativos) o trimestral (elementos estructurales). | D24: Reevaluar semestralmente · Plan de acción ≤ 90 días
B25: Bajo (3 - 5) | C25: Inspección semestral. | D25: Reevaluar anualmente · Se gestiona con la rutina normal
B26: Muy bajo (1 - 2) | C26: Inspección anual. | D26: Reevaluar anualmente · Riesgo aceptable, solo monitoreo
A28: ADVERTENCIAS DE USO
B29: · Las calificaciones precargadas (Probabilidad e Impacto) son valores típicos de riesgo INHERENTE para un CEDI convencional, es decir, sin descontar la eficacia de los controles instalados. NO son un diagnóstico: deben ajustarse con datos del sitio.
B30: · Por eso la mayoría de los riesgos aparece inicialmente en nivel Alto: son escenarios con consecuencia grave o fatal. A medida que verifique controles eficaces y baje la probabilidad, obtendrá el riesgo residual, que es el que realmente se gestiona.
B31: · La frecuencia calculada por criticidad es un mínimo de gestión. Cuando una norma, la aseguradora o el fabricante exijan una frecuencia mayor, prevalece la más exigente.
B32: · Las referencias legales citadas incluyen normativa colombiana (NSR-10, RETIE, Decreto 1072 de 2015, Resolución 0312 de 2019, entre otras) y estándares internacionales (NFPA, EN, ISO, OSHA). Valide siempre la normativa vigente de su jurisdicción.
B33: · La inspección experta anual de estantería y la evaluación estructural deben hacerlas terceros técnicamente competentes; este checklist no los reemplaza.

Sheet 1. Caracterización CEDI
B2: FICHA DE CARACTERIZACIÓN DEL CENTRO DE DISTRIBUCIÓN
B3: Insumo obligatorio para calificar los riesgos. Cada variable es un modificador de la probabilidad o del impacto.
A5: 1. IDENTIFICACIÓN Y GENERALIDADES
A6: # | B6: Variable a caracterizar | C6: Valor / respuesta | D6: Unidad o formato | E6: Por qué importa para la calificación del riesgo
A7: 1 | B7: Nombre / código del centro de distribución | D7: Texto | E7: Identifica el activo dentro de la red logística.
A8: 2 | B8: Dirección, ciudad y país | D8: Texto | E8: Define el marco legal aplicable y la amenaza natural y social del sitio.
A9: 3 | B9: Coordenadas geográficas | D9: Lat / Long | E9: Permite cruzar con mapas de amenaza sísmica, inundación y criminalidad.
A10: 4 | B10: Año de construcción y de la última ampliación | D10: Año | E10: Indica bajo qué código de construcción fue diseñado (norma sísmica vigente en su momento).
A11: 5 | B11: Tenencia: propio / arrendado / operado por 3PL | D11: Selección | E11: Determina quién responde por la infraestructura y qué se puede modificar.
A12: 6 | B12: Certificaciones vigentes (ISO 9001/14001/45001, BASC, OEA, BPM, HACCP) | D12: Texto | E12: Evidencia madurez del sistema de gestión y reduce la probabilidad de fallas sistémicas.
A13: 7 | B13: Turnos y días de operación (24/7, 2 turnos, etc.) | D13: Texto | E13: Mayor exposición horaria = mayor probabilidad de eventos; obliga a cobertura de brigada por turno.
A14: 8 | B14: Número de personas: directas / temporales / contratistas | D14: Personas | E14: Define la magnitud de la consecuencia humana y la carga de inducción y entrenamiento.
A16: 2. INFRAESTRUCTURA Y DIMENSIONES
A17: # | B17: Variable a caracterizar | C17: Valor / respuesta | D17: Unidad o formato | E17: Por qué importa para la calificación del riesgo
A18: 1 | B18: Área total del lote y área construida cubierta | D18: m² | E18: Escala del impacto potencial y requisitos de sectorización y de protección contra incendio.
A19: 2 | B19: Número de bodegas o sectores independientes | D19: Número | E19: La compartimentación limita la propagación y la pérdida máxima probable.
A20: 3 | B20: Altura libre a la viga inferior / a la cubierta | D20: m | E20: Determina el tipo de rociador requerido y la severidad de un incendio en altura.
A21: 4 | B21: Altura máxima de almacenamiento | D21: m | E21: Por encima de 7,6 m cambian los criterios de protección contra incendio y de estabilidad.
A22: 5 | B22: Capacidad portante de la losa | D22: t/m² o kN/m² | E22: Restringe carga puntual de montantes, tránsito de equipos y peso por posición.
A23: 6 | B23: Tipo de cubierta y sistema de drenaje | D23: Texto | E23: Riesgo de colapso por granizo o agua empozada y de daño masivo por filtración.
A24: 7 | B24: Sectorización: muros y puertas cortafuego | D24: Sí / No + descripción | E24: Es el control que evita que un incendio se convierta en pérdida total.
A25: 8 | B25: Zonas especiales: cuarto frío, jaula de valor, MERPEL, inflamables, mezanine | D25: Texto | E25: Cada zona añade riesgos específicos y requisitos legales propios.
A27: 3. VOLUMEN, INVENTARIO Y PRODUCTO
A28: # | B28: Variable a caracterizar | C28: Valor / respuesta | D28: Unidad o formato | E28: Por qué importa para la calificación del riesgo
A29: 1 | B29: Número de posiciones de estiba (pallet) instaladas | D29: Posiciones | E29: Base para calcular ocupación; la ocupación alta multiplica casi todos los riesgos operativos.
A30: 2 | B30: Ocupación promedio y ocupación pico | D30: % | E30: Por encima del 85-90% aparecen bloqueos de pasillos, almacenamiento improvisado y accidentes.
A31: 3 | B31: SKU activos y clasificación ABC | D31: Número / % | E31: Complejidad operativa, errores de picking y necesidad de conteos cíclicos.
A32: 4 | B32: Unidades, cajas o pallets movidos por día (entradas y salidas) | D32: Unid/día | E32: Throughput = exposición: a más movimientos, más probabilidad de colisión, avería y error.
A33: 5 | B33: Rotación del inventario (turns/año) y días de inventario | D33: Número | E33: Baja rotación concentra valor y aumenta obsolescencia y carga de fuego permanente.
A34: 6 | B34: Valor promedio del inventario y valor pico | D34: Moneda | E34: Define el impacto económico y debe compararse contra el valor asegurado.
A35: 7 | B35: Estacionalidad (meses pico y % de incremento) | D35: % | E35: Los picos son el momento de mayor accidentalidad y desorden.
A36: 8 | B36: Familias de producto y clasificación de mercancía para incendio (Clase I-IV, plásticos) | D36: Texto | E36: Determina si el sistema de rociadores instalado sigue siendo válido.
A37: 9 | B37: ¿Maneja mercancías peligrosas? Clases ONU presentes | D37: Sí / No + clases | E37: Activa requisitos de segregación, rotulado, FDS, kit de derrames y formación.
A38: 10 | B38: ¿Maneja cadena de frío? Rangos de temperatura | D38: Sí / No + °C | E38: Añade riesgo de pérdida total del lote por falla de equipo o de energía.
A39: 11 | B39: ¿Producto de alto valor o de alto riesgo de hurto? | D39: Sí / No | E39: Define necesidad de jaula, CCTV dedicado y controles de seguridad reforzados.
A40: 12 | B40: ¿Alimentos, farmacéuticos o producto regulado? | D40: Sí / No | E40: Añade riesgo sanitario, trazabilidad, recall y sanción del ente regulador.
A42: 4. SISTEMA DE ALMACENAMIENTO
A43: # | B43: Variable a caracterizar | C43: Valor / respuesta | D43: Unidad o formato | E43: Por qué importa para la calificación del riesgo
A44: 1 | B44: Tipos de estantería (selectiva, doble profundidad, drive-in, push back, dinámica, cantilever, automatizada) | D44: Texto | E44: Cada sistema tiene modos de falla y frecuencias de inspección distintas.
A45: 2 | B45: Fabricante, año de instalación y memoria de cálculo disponible | D45: Texto / Sí-No | E45: Sin memoria de cálculo no hay forma de verificar la capacidad real.
A46: 3 | B46: Placas de carga instaladas y visibles | D46: Sí / No / Parcial | E46: Es el control primario contra la sobrecarga de estantería.
A47: 4 | B47: ¿Existe PRRS designado (responsable de seguridad de estanterías)? | D47: Sí / No + nombre | E47: Requisito de EN 15635 para el ciclo de inspección semanal y el reporte de daños.
A48: 5 | B48: Fecha de la última inspección experta de estantería | D48: Fecha | E48: Si supera 12 meses, el riesgo de colapso se califica al alza.
A49: 6 | B49: Nivel de daño acumulado (rojo / ámbar / verde) del último informe | D49: Número por color | E49: Los daños rojos exigen descarga y bloqueo inmediato.
A50: 7 | B50: Ancho de pasillo de trabajo y tipo de pasillo (convencional, estrecho, muy estrecho) | D50: m | E50: Pasillos estrechos aumentan la probabilidad de impacto contra montantes.
A51: 8 | B51: Tipo, medida y estado de las estibas o pallets | D51: Texto | E51: Estibas deterioradas son causa frecuente de caída de carga desde altura.
A52: 9 | B52: ¿Almacenamiento en bloque / apilado en piso? Altura máxima | D52: Sí / No + m | E52: Riesgo de volcamiento de rumas y de bloqueo de rutas.
A54: 5. EQUIPOS DE MANIPULACIÓN (MHE)
A55: # | B55: Variable a caracterizar | C55: Valor / respuesta | D55: Unidad o formato | E55: Por qué importa para la calificación del riesgo
A56: 1 | B56: Cantidad y tipo de equipos (contrabalanceado, retráctil, apilador, transpaleta, orderpicker, trilateral) | D56: Número por tipo | E56: Define el perfil de accidentalidad y los programas de mantenimiento y certificación.
A57: 2 | B57: Fuente de energía (eléctrica, GLP, diésel) y edad promedio de la flota | D57: Texto / años | E57: GLP y diésel añaden riesgo de incendio y CO; flotas viejas fallan más.
A58: 3 | B58: ¿Sala de carga de baterías? Tecnología (plomo-ácido / ion-litio) | D58: Sí / No + tipo | E58: Plomo-ácido: hidrógeno y ácido. Litio: fuga térmica de difícil extinción.
A59: 4 | B59: Número de operadores certificados vs. número de equipos | D59: Número | E59: Déficit de operadores certificados obliga a suplencias improvisadas.
A60: 5 | B60: ¿Sistemas de seguridad instalados (anticolisión, telemetría, limitador de velocidad, luces azules)? | D60: Texto | E60: Reducen fuertemente la probabilidad de atropellamiento y volcamiento.
A61: 6 | B61: Cumplimiento del plan de mantenimiento preventivo | D61: % | E61: Es el mejor predictor de falla mecánica en operación.
A63: 6. MUELLES, PATIOS Y TRANSPORTE
A64: # | B64: Variable a caracterizar | C64: Valor / respuesta | D64: Unidad o formato | E64: Por qué importa para la calificación del riesgo
A65: 1 | B65: Número de muelles de recibo y de despacho | D65: Número | E65: Define capacidad, congestión y exposición del punto más crítico del CEDI.
A66: 2 | B66: Tipo de muelle (a nivel, elevado con nivelador, rampa) y capacidad del nivelador | D66: Texto / kg | E66: Los muelles concentran los accidentes graves con montacargas y camiones.
A67: 3 | B67: ¿Dock lock, calzos y semáforos de muelle? | D67: Sí / No | E67: Control clave contra el desplazamiento del vehículo durante el cargue.
A68: 4 | B68: Área de patio, capacidad de parqueo y zona de espera de conductores | D68: m² / vehículos | E68: Patios pequeños generan maniobras riesgosas y filas en la vía pública.
A69: 5 | B69: ¿Sistema de citas / agendamiento de vehículos? | D69: Sí / No | E69: Sin citas, el pico de llegadas produce congestión y presión sobre la operación.
A70: 6 | B70: Vehículos atendidos por día y tipo (turbo, sencillo, tractomula, contenedor) | D70: Número / tipo | E70: Define el tránsito interno y la exposición peatón-vehículo.
A71: 7 | B71: ¿Opera exportación en contenedor? | D71: Sí / No | E71: Activa el riesgo de contaminación de la carga y requisitos BASC / OEA / C-TPAT.
A73: 7. PROTECCIÓN CONTRA INCENDIO Y SERVICIOS
A74: # | B74: Variable a caracterizar | C74: Valor / respuesta | D74: Unidad o formato | E74: Por qué importa para la calificación del riesgo
A75: 1 | B75: Sistema de rociadores: tipo (ESFR, techo, in-rack), año y última certificación | D75: Texto / fecha | E75: Es el control decisivo entre un conato y una pérdida total.
A76: 2 | B76: Reserva de agua contra incendio y bomba (tipo y prueba anual) | D76: m³ / Sí-No | E76: Sin agua suficiente el sistema no cumple su función de diseño.
A77: 3 | B77: Detección y alarma: cobertura y última prueba funcional | D77: Texto / fecha | E77: Determina el tiempo de detección y de evacuación.
A78: 4 | B78: Número de extintores, gabinetes e hidrantes; fecha de última recarga | D78: Número / fecha | E78: Primera línea de respuesta ante conato.
A79: 5 | B79: Distancia y tiempo de respuesta del cuerpo de bomberos; hidrantes públicos cercanos | D79: km / min | E79: Un tiempo de respuesta alto obliga a mayor autoprotección.
A80: 6 | B80: Subestación (kVA), planta eléctrica y UPS: alcance y prueba con carga | D80: Texto | E80: Define qué sobrevive a un corte de energía: WMS, frío, CCTV, control de acceso.
A81: 7 | B81: Fecha de la última termografía de tableros eléctricos | D81: Fecha | E81: La falla eléctrica es una de las principales causas de incendio en bodegas.
A83: 8. ENTORNO, AMENAZA NATURAL Y SEGURIDAD
A84: # | B84: Variable a caracterizar | C84: Valor / respuesta | D84: Unidad o formato | E84: Por qué importa para la calificación del riesgo
A85: 1 | B85: Zona de amenaza sísmica (baja / intermedia / alta) y aceleración de diseño | D85: Texto / Aa | E85: Modifica directamente el riesgo de colapso estructural y de estantería.
A86: 2 | B86: ¿El diseño de la estantería contempló carga sísmica? | D86: Sí / No / Se desconoce | E86: Sin diseño sísmico, un sismo moderado puede colapsar la estantería llena.
A87: 3 | B87: ¿Zona inundable? Nivel del piso respecto a la vía y a cuerpos de agua cercanos | D87: Sí / No + m | E87: Define si se puede almacenar producto directamente en piso y el riesgo de pérdida masiva.
A88: 4 | B88: Amenaza por vientos fuertes, granizo, deslizamiento o incendio forestal | D88: Texto | E88: Determina requisitos de cubierta, anclajes y protocolos de alerta.
A89: 5 | B89: Ocupantes colindantes y actividades peligrosas cercanas (radio de 500 m) | D89: Texto | E89: Un siniestro del vecino puede destruir el CEDI o forzar su evacuación.
A90: 6 | B90: Nivel de criminalidad de la zona e histórico de asalto o hurto | D90: Texto | E90: Modifica el riesgo de seguridad física y los controles exigidos por la aseguradora.
A91: 7 | B91: Vías de acceso, restricciones de horario y riesgo de bloqueos | D91: Texto | E91: Afecta continuidad, cumplimiento de entregas y respuesta de emergencia.
A93: 9. GESTIÓN, SISTEMAS Y ASEGURAMIENTO
A94: # | B94: Variable a caracterizar | C94: Valor / respuesta | D94: Unidad o formato | E94: Por qué importa para la calificación del riesgo
A95: 1 | B95: WMS / ERP utilizados y esquema de respaldo y alta disponibilidad | D95: Texto | E95: Su caída paraliza el 100% de la operación en un CEDI moderno.
A96: 2 | B96: ¿Procedimiento manual de contingencia probado? | D96: Sí / No + fecha | E96: Es la diferencia entre operar degradado y detenerse por completo.
A97: 3 | B97: Aseguradora, valores asegurados (edificio, contenido, lucro cesante) y deducibles | D97: Moneda | E97: Define cuánto de la pérdida es realmente transferida.
A98: 4 | B98: Recomendaciones de la última inspección de la aseguradora y su estado de cierre | D98: Texto | E98: Recomendaciones abiertas pueden invalidar la indemnización.
A99: 5 | B99: Histórico de eventos de los últimos 5 años (incendios, colapsos, accidentes, hurtos, inundaciones) | D99: Texto | E99: La frecuencia histórica es el mejor estimador de la probabilidad futura.
A100: 6 | B100: Indicadores actuales: accidentalidad, pérdida desconocida, ERI, averías, ocupación | D100: Números | E100: Permiten calificar con datos y no con percepción.
A101: 7 | B101: ¿Existe plan de continuidad del negocio (BCP) probado? | D101: Sí / No + fecha | E101: Determina el tiempo de recuperación tras un siniestro mayor.

Sheet 2. Matriz de Riesgos
A1: MATRIZ DE RIESGOS Y CHECKLIST DE VERIFICACIÓN — CENTRO DE DISTRIBUCIÓN
A2: P e I precargados = riesgo INHERENTE típico (sin descontar la eficacia de los controles del sitio): AJÚSTELOS con la caracterización. Si al verificar en campo el control existe y es eficaz, baje la probabilidad — eso es el riesgo residual. · P×I, Nivel y Frecuencia mínima se calculan solos. · Entre la frecuencia calculada y la técnica, prevalece la más exigente.
A4: ID | B4: Categoría de riesgo | C4: Elemento / componente | D4: Evento de riesgo (qué puede pasar) | E4: Causas y factores desencadenantes | F4: Consecuencia potencial | G4: QUÉ VERIFICAR (punto de control del checklist) | H4: Evidencia o registro esperado | I4: P | J4: I | K4: P×I | L4: Nivel | M4: Frecuencia mínima según criticidad (calculada) | N4: Frecuencia técnica recomendada (norma / buena práctica) | O4: Referencia normativa o estándar | P4: Responsable | Q4: Cumple | R4: Hallazgo / observación | S4: Acción requerida | T4: Fecha límite
A5: A-01 | B5: A. Infraestructura y edificio | C5: Estructura portante (columnas, cerchas) | D5: Deterioro, corrosión o daño estructural por impacto de equipos | E5: Impactos de montacargas sin protección; corrosión por humedad/salinidad; falta de mantenimiento; sobrecarga de cubierta | F5: Colapso parcial o total, fatalidades, pérdida total del inventario, paro prolongado | G5: Inspección visual de columnas, bases, placas y arriostramientos; verificar protectores en columnas expuestas a tránsito | H5: Informe de evaluación estructural firmado por ingeniero; registro fotográfico | I5: 2 | J5: 5 | K5: =IF(OR($I5="",$J5=""),"",$I5*$J5) -> 10 | L5: =IF($K5="","",IF($K5>=20,"Extremo",IF($K5>=12,"Alto",IF($K5>=6,"Medio",IF($K5>=3,"Bajo","Muy bajo"))))) -> Medio | M5: =IFERROR(VLOOKUP($L5,'3. Escalas y Criterios'!$A$30:$C$34,3,FALSE),"") -> Mensual para elementos operativos; trimestral para elementos estructurales o de instalación | N5: Visual mensual; evaluación estructural profesional cada 1-3 años y después de sismo/impacto mayor | O5: NSR-10 / IBC; ISO 31000 | P5: Mantenimiento / Ingeniería
A6: A-02 | B6: A. Infraestructura y edificio | C6: Cubierta y sistema de drenaje | D6: Colapso o filtración por acumulación de agua, granizo u obstrucción de canales | E6: Canaletas y bajantes obstruidas; láminas corroidas; pendiente insuficiente; granizada intensa | F6: Daño masivo de producto por agua, colapso de cubierta, paro operativo, reclamo de seguro | G6: Revisar canales, bajantes, tragantes, sellos de lucernarios y fijaciones; medir espesor/corrosión | H6: Orden de trabajo de limpieza de cubierta; registro fotográfico antes/después | I6: 3 | J6: 4 | K6: =IF(OR($I6="",$J6=""),"",$I6*$J6) -> 12 | L6: =IF($K6="","",IF($K6>=20,"Extremo",IF($K6>=12,"Alto",IF($K6>=6,"Medio",IF($K6>=3,"Bajo","Muy bajo"))))) -> Alto | M6: =IFERROR(VLOOKUP($L6,'3. Escalas y Criterios'!$A$30:$C$34,3,FALSE),"") -> Semanal (verificación) + inspección formal mensual documentada | N6: Limpieza y revisión trimestral y obligatoria antes de temporada de lluvias | O6: Manual del fabricante; póliza de seguro | P6: Mantenimiento
A7: A-03 | B7: A. Infraestructura y edificio | C7: Piso industrial / losa | D7: Fisuras, hundimientos o capacidad portante insuficiente (t/m2) | E7: Diseño original inferior a la carga actual de racks; juntas deterioradas; humedad en subrasante; cambio de sistema de almacenamiento | F7: Desnivel de estantería y riesgo de colapso, daño de MHE, accidentes por caída | G7: Verificar planitud, estado de juntas, fisuras bajo placas base, capacidad de diseño vs. carga puntual de montantes | H7: Estudio de piso / memoria de capacidad portante; reporte de nivelación | I7: 3 | J7: 4 | K7: =IF(OR($I7="",$J7=""),"",$I7*$J7) -> 12 | L7: =IF($K7="","",IF($K7>=20,"Extremo",IF($K7>=12,"Alto",IF($K7>=6,"Medio",IF($K7>=3,"Bajo","Muy bajo"))))) -> Alto | M7: =IFERROR(VLOOKUP($L7,'3. Escalas y Criterios'!$A$30:$C$34,3,FALSE),"") -> Semanal (verificación) + inspección formal mensual documentada | N7: Inspección visual semestral; estudio técnico ante cambio de sistema de almacenamiento | O7: EN 15620; ACI 302 / NSR-10 | P7: Mantenimiento / Ingeniería
A8: A-04 | B8: A. Infraestructura y edificio | C8: Sectorización y muros cortafuego | D8: Pérdida de la sectorización contra incendio | E8: Perforaciones sin sellar para ductos/cables; puertas cortafuego bloqueadas o con cuña; muros incompletos hasta cubierta | F8: Propagación de incendio a toda la bodega; pérdida total; incumplimiento de garantía de la póliza | G8: Verificar sellos cortafuego, cierre automático de puertas, ausencia de obstrucciones y continuidad del muro | H8: Certificado de sellos cortafuego; checklist de puertas | I8: 3 | J8: 5 | K8: =IF(OR($I8="",$J8=""),"",$I8*$J8) -> 15 | L8: =IF($K8="","",IF($K8>=20,"Extremo",IF($K8>=12,"Alto",IF($K8>=6,"Medio",IF($K8>=3,"Bajo","Muy bajo"))))) -> Alto | M8: =IFERROR(VLOOKUP($L8,'3. Escalas y Criterios'!$A$30:$C$34,3,FALSE),"") -> Semanal (verificación) + inspección formal mensual documentada | N8: Trimestral | O8: NFPA 221 / NFPA 80 | P8: Mantenimiento / HSE
A9: A-05 | B9: A. Infraestructura y edificio | C9: Cerramiento, cubierta y humedad | D9: Ingreso de agua, polvo o plagas por deterioro de la envolvente | E9: Sellos de muelle deteriorados; láminas sueltas; ventanas rotas; falta de barreras | F9: Daño y contaminación de producto, no conformidad sanitaria | G9: Inspección perimetral de muros, techos, sellos, mallas y sifones | H9: Checklist de infraestructura; registro MIP | I9: 3 | J9: 3 | K9: =IF(OR($I9="",$J9=""),"",$I9*$J9) -> 9 | L9: =IF($K9="","",IF($K9>=20,"Extremo",IF($K9>=12,"Alto",IF($K9>=6,"Medio",IF($K9>=3,"Bajo","Muy bajo"))))) -> Medio | M9: =IFERROR(VLOOKUP($L9,'3. Escalas y Criterios'!$A$30:$C$34,3,FALSE),"") -> Mensual para elementos operativos; trimestral para elementos estructurales o de instalación | N9: Semestral | O9: BPM / HACCP (si aplica alimentos) | P9: Mantenimiento / Calidad
A10: A-06 | B10: A. Infraestructura y edificio | C10: Altura libre y espacio bajo rociadores | D10: Almacenamiento por encima de la altura de diseño | E10: Presión por capacidad; ausencia de topes o indicadores de altura máxima | F10: Falla del sistema de rociadores en incendio; siniestro no cubierto por la póliza | G10: Medir distancia libre entre la carga y el deflector del rociador (mínimo 45 cm) y respetar altura máxima de almacenamiento | H10: Registro de medición; señalización de altura máxima en pasillos | I10: 4 | J10: 5 | K10: =IF(OR($I10="",$J10=""),"",$I10*$J10) -> 20 | L10: =IF($K10="","",IF($K10>=20,"Extremo",IF($K10>=12,"Alto",IF($K10>=6,"Medio",IF($K10>=3,"Bajo","Muy bajo"))))) -> Extremo | M10: =IFERROR(VLOOKUP($L10,'3. Escalas y Criterios'!$A$30:$C$34,3,FALSE),"") -> Diaria o por turno (verificación operativa) + inspección formal semanal documentada | N10: Mensual (y en cada auditoría de layout) | O10: NFPA 13 | P10: Jefe de CEDI / HSE
A11: B-01 | B11: B. Estantería y sistemas de almacenamiento | C11: Racks selectivos - capacidad de carga | D11: Sobrecarga de estantería por exceder capacidad por nivel o por módulo | E11: Ausencia de placas de carga; pallets más pesados que el diseño; cambio de producto sin recálculo; desconocimiento del operador | F11: Colapso progresivo (efecto domino) con fatalidades y pérdida total de inventario | G11: Verificar existencia y vigencia de placas de carga visibles por módulo; comparar peso real del pallet vs. capacidad declarada | H11: Memoria de cálculo del fabricante; placas de carga; muestreo de pesaje de pallets | I11: 4 | J11: 5 | K11: =IF(OR($I11="",$J11=""),"",$I11*$J11) -> 20 | L11: =IF($K11="","",IF($K11>=20,"Extremo",IF($K11>=12,"Alto",IF($K11>=6,"Medio",IF($K11>=3,"Bajo","Muy bajo"))))) -> Extremo | M11: =IFERROR(VLOOKUP($L11,'3. Escalas y Criterios'!$A$30:$C$34,3,FALSE),"") -> Diaria o por turno (verificación operativa) + inspección formal semanal documentada | N11: Verificación visual semanal; inspección experta anual por tercero competente | O11: EN 15635 / EN 15512 / RMI ANSI MH16.1 | P11: PRRS - Responsable de Seguridad de Estantería
A12: B-02 | B12: B. Estantería y sistemas de almacenamiento | C12: Racks - daño por impacto | D12: Montantes, diagonales o vigas deformados por impacto de MHE | E12: Pasillos estrechos; velocidad excesiva; falta de protectores; operadores sin destreza; iluminación deficiente | F12: Pérdida de capacidad estructural (hasta 70%) y colapso de la línea de racks | G12: Recorrido de inspección con clasificación de daño por semáforo: VERDE (monitorear), ÁMBAR (reparar programado), ROJO (descargar y bloquear de inmediato) | H12: Formato de inspección de estantería con código de módulo y nivel; fotos; ordenes de reparación | I12: 4 | J12: 5 | K12: =IF(OR($I12="",$J12=""),"",$I12*$J12) -> 20 | L12: =IF($K12="","",IF($K12>=20,"Extremo",IF($K12>=12,"Alto",IF($K12>=6,"Medio",IF($K12>=3,"Bajo","Muy bajo"))))) -> Extremo | M12: =IFERROR(VLOOKUP($L12,'3. Escalas y Criterios'!$A$30:$C$34,3,FALSE),"") -> Diaria o por turno (verificación operativa) + inspección formal semanal documentada | N12: Reporte inmediato por cualquier trabajador; inspección visual semanal por el PRRS; inspección experta anual | O12: EN 15635 sección 9 | P12: PRRS / Jefe de CEDI
A13: B-03 | B13: B. Estantería y sistemas de almacenamiento | C13: Racks - anclaje al piso | D13: Montantes sin anclaje, con anclaje flojo o placa base fisurada | E13: Montaje deficiente; reubicación de racks sin reanclar; losa deteriorada; ausencia de torque especificado | F13: Volcamiento de la línea de estantería, especialmente ante sismo o impacto | G13: Verificar presencia, cantidad y torque de pernos de anclaje; estado de placas base y nivelación | H13: Protocolo de torque; registro de montaje; certificado del instalador | I13: 3 | J13: 5 | K13: =IF(OR($I13="",$J13=""),"",$I13*$J13) -> 15 | L13: =IF($K13="","",IF($K13>=20,"Extremo",IF($K13>=12,"Alto",IF($K13>=6,"Medio",IF($K13>=3,"Bajo","Muy bajo"))))) -> Alto | M13: =IFERROR(VLOOKUP($L13,'3. Escalas y Criterios'!$A$30:$C$34,3,FALSE),"") -> Semanal (verificación) + inspección formal mensual documentada | N13: Anual (y 100% tras reubicación o sismo) | O13: EN 15629 / EN 15635 | P13: PRRS / Mantenimiento
A14: B-04 | B14: B. Estantería y sistemas de almacenamiento | C14: Racks - conectores y pasadores de seguridad | D14: Vigas sin pasador o clip de seguridad | E14: Pérdida durante el montaje o reconfiguración; no reposición tras cambio de nivel | F14: Desenganche de la viga al elevar el pallet; caída de carga sobre personal | G14: Verificación muestreada de pasadores en 100% de vigas por zona | H14: Checklist de inspección visual; registro de reposición | I14: 3 | J14: 5 | K14: =IF(OR($I14="",$J14=""),"",$I14*$J14) -> 15 | L14: =IF($K14="","",IF($K14>=20,"Extremo",IF($K14>=12,"Alto",IF($K14>=6,"Medio",IF($K14>=3,"Bajo","Muy bajo"))))) -> Alto | M14: =IFERROR(VLOOKUP($L14,'3. Escalas y Criterios'!$A$30:$C$34,3,FALSE),"") -> Semanal (verificación) + inspección formal mensual documentada | N14: Mensual (muestreo por zona) + tras cada reconfiguración | O14: EN 15635 | P14: PRRS
A15: B-05 | B15: B. Estantería y sistemas de almacenamiento | C15: Racks - protección perimetral | D15: Ausencia de protectores de columna, guardarrail de fin de pasillo y topes de pallet | E15: No incluidos en el diseño; retirados por mantenimiento; deterioro por impactos previos | F15: Impacto directo sobre montantes y colapso; empuje del pallet hacia el pasillo contrario | G15: Verificar protectores en columnas de esquina, extremos de pasillo, zonas de tránsito y cerca de muelles | H15: Plano de protección perimetral; checklist | I15: 4 | J15: 3 | K15: =IF(OR($I15="",$J15=""),"",$I15*$J15) -> 12 | L15: =IF($K15="","",IF($K15>=20,"Extremo",IF($K15>=12,"Alto",IF($K15>=6,"Medio",IF($K15>=3,"Bajo","Muy bajo"))))) -> Alto | M15: =IFERROR(VLOOKUP($L15,'3. Escalas y Criterios'!$A$30:$C$34,3,FALSE),"") -> Semanal (verificación) + inspección formal mensual documentada | N15: Mensual | O15: EN 15512 anexo / buena práctica | P15: Mantenimiento / HSE
A16: B-06 | B16: B. Estantería y sistemas de almacenamiento | C16: Racks - modificaciones de configuración | D16: Cambio de niveles o de configuración sin recálculo estructural | E16: Reslotting; nuevos formatos de pallet; decisión operativa sin consulta técnica | F16: Pérdida de capacidad y colapso; anulación de la garantía del fabricante | G16: Verificar autorización técnica escrita para todo cambio de altura de viga o de configuración, y actualización de placas de carga | H16: Aval escrito del fabricante o ingeniero calculista; placas actualizadas | I16: 3 | J16: 5 | K16: =IF(OR($I16="",$J16=""),"",$I16*$J16) -> 15 | L16: =IF($K16="","",IF($K16>=20,"Extremo",IF($K16>=12,"Alto",IF($K16>=6,"Medio",IF($K16>=3,"Bajo","Muy bajo"))))) -> Alto | M16: =IFERROR(VLOOKUP($L16,'3. Escalas y Criterios'!$A$30:$C$34,3,FALSE),"") -> Semanal (verificación) + inspección formal mensual documentada | N16: En cada cambio + verificación anual de configuración vs. plano aprobado | O16: EN 15635 / EN 15629 | P16: Jefe de CEDI / PRRS
... A122: O-07 | B122: O. Legal, financiero y continuidad | C122: Historial de siniestros y lecciones aprendidas | D122: Repetición de eventos por falta de análisis de causa raíz | E122: Investigaciones superficiales; acciones sin cierre ni verificación de eficacia; ausencia de tendencia de casi-accidentes | F122: Recurrencia de accidentes y pérdidas evitables | G122: Verificar investigación de todos los eventos (incluidos casi-accidentes), análisis de causa raíz, cierre y verificación de eficacia | H122: Registro de investigaciones; matriz de acciones con verificación de eficacia | I122: 3 | J122: 4 | K122: =IF(OR($I122="",$J122=""),"",$I122*$J122) -> 12 | L122: =IF($K122="","",IF($K122>=20,"Extremo",IF($K122>=12,"Alto",IF($K122>=6,"Medio",IF($K122>=3,"Bajo","Muy bajo"))))) -> Alto | M122: =IFERROR(VLOOKUP($L122,'3. Escalas y Criterios'!$A$30:$C$34,3,FALSE),"") -> Semanal (verificación) + inspección formal mensual documentada | N122: Mensual (revisión de eventos) + análisis de tendencia trimestral | O122: ISO 45001 / ISO 31000 | P122: HSE / Jefe de CEDI

Sheet 3. Escalas y Criterios
A1: ESCALAS DE VALORACIÓN, MATRIZ DE RIESGO Y CRITERIOS DE FRECUENCIA
A2: Metodología ISO 31000 · Riesgo = Probabilidad × Impacto
A3: ESCALA DE PROBABILIDAD (qué tan factible es que ocurra)
A4: Valor | B4: Descriptor | C4: Criterio de frecuencia esperada | D4: Criterio histórico en la instalación | E4: Criterio de control
A5: 1 | B5: Raro | C5: Podría ocurrir solo en circunstancias excepcionales (menos de 1 vez cada 10 años) | D5: Nunca ha ocurrido en el CEDI ni en instalaciones similares del sector | E5: Controles robustos, verificados y con evidencia
A6: 2 | B6: Improbable | C6: Podría ocurrir alguna vez (1 vez cada 5 a 10 años) | D6: Ha ocurrido en el sector, no en esta instalación | E6: Controles existen y funcionan, con desviaciones menores
A7: 3 | B7: Posible | C7: Podría ocurrir en algún momento (1 vez cada 1 a 5 años) | D7: Ha ocurrido al menos una vez en esta instalación o en la red | E7: Controles existen pero su cumplimiento es irregular
A8: 4 | B8: Probable | C8: Ocurrirá probablemente en la mayoría de las circunstancias (varias veces al año) | D8: Ocurre de forma recurrente; hay reportes o casi-accidentes frecuentes | E8: Controles débiles, informales o sin seguimiento
A9: 5 | B9: Casi seguro | C9: Se espera que ocurra en la mayoría de las circunstancias (mensual o más frecuente) | D9: Ocurre habitualmente; es parte del día a día de la operación | E9: No hay control o el control está fuera de servicio
A11: ESCALA DE IMPACTO / CONSECUENCIA (se toma el peor de los criterios)
A12: Valor | B12: Descriptor | C12: Personas (SST) | D12: Operación y continuidad | E12: Económico y patrimonial | F12: Legal, sanitario y reputacional
A13: 1 | B13: Insignificante | C13: Sin lesión o atención de primeros auxilios | D13: Sin afectación del servicio | E13: Pérdida marginal, absorbida por la operación | F13: Sin consecuencia legal ni externa
A14: 2 | B14: Menor | C14: Lesión leve sin incapacidad | D14: Retraso puntual de horas en un proceso | E14: Pérdida menor, cubierta por el presupuesto de mantenimiento | F14: Observación interna o de auditoría
A15: 3 | B15: Moderado | C15: Lesión con incapacidad temporal | D15: Paro de un turno o de un proceso completo; incumplimiento de despachos del día | E15: Pérdida significativa; se afecta el resultado del mes | F15: Requerimiento de la autoridad, reclamo formal de cliente
A16: 4 | B16: Mayor | C16: Lesión grave, incapacidad permanente parcial o varios lesionados | D16: Paro de varios días o pérdida parcial de la capacidad de almacenamiento | E16: Pérdida patrimonial importante; supera el deducible y afecta el resultado del año | F16: Sanción económica, suspensión parcial, daño reputacional en medios
A17: 5 | B17: Catastrófico | C17: Una o varias fatalidades o incapacidad permanente total | D17: Pérdida del CEDI o interrupción prolongada del abastecimiento a la red | E17: Pérdida total o no asegurada; compromete la viabilidad del negocio | F17: Cierre del establecimiento, responsabilidad penal, recall masivo
A19: MATRIZ DE CALIFICACIÓN 5 × 5 (filas = Probabilidad · columnas = Impacto)
A20: P \ I | B20: 1 | C20: 2 | D20: 3 | E20: 4 | F20: 5
A21: 5 | B21: 5 | C21: 10 | D21: 15 | E21: 20 | F21: 25
A22: 4 | B22: 4 | C22: 8 | D22: 12 | E22: 16 | F22: 20
A23: 3 | B23: 3 | C23: 6 | D23: 9 | E23: 12 | F23: 15
A24: 2 | B24: 2 | C24: 4 | D24: 6 | E24: 8 | F24: 10
A25: 1 | B25: 1 | C25: 2 | D25: 3 | E25: 4 | F25: 5
A27: Nota: si el escenario puede causar una fatalidad, califique el impacto en 5 aunque la probabilidad sea baja; ese riesgo se gestiona por severidad, no por frecuencia.
A28: NIVELES DE RIESGO: FRECUENCIA DE REVISIÓN Y RESPUESTA EXIGIDA
A29: Nivel de riesgo | B29: Rango (P × I) | C29: Frecuencia mínima de verificación en campo | D29: Reevaluación formal del riesgo | E29: Plazo máximo del plan de acción | F29: Quién acepta / aprueba
A30: Extremo | B30: 20 - 25 | C30: Diaria o por turno (verificación operativa) + inspección formal semanal documentada | D30: Mensual | E30: ≤ 15 días · Se exige control inmediato o suspensión de la actividad | F30: Gerencia / Dirección
A31: Alto | B31: 12 - 16 | C31: Semanal (verificación) + inspección formal mensual documentada | D31: Trimestral | E31: ≤ 30 días | F31: Jefe de CEDI con visto bueno de HSE
A32: Medio | B32: 6 - 10 | C32: Mensual para elementos operativos; trimestral para elementos estructurales o de instalación | D32: Semestral | E32: ≤ 90 días | F32: Jefe de CEDI
A33: Bajo | B33: 3 - 5 | C33: Semestral | D33: Anual | E33: Siguiente ciclo presupuestal | F33: Coordinador del proceso
A34: Muy bajo | B34: 1 - 2 | C34: Anual | D34: Anual | E34: Se monitorea, no requiere acción | F34: Coordinador del proceso
A36: DISPARADORES DE REVISIÓN EXTRAORDINARIA (obligan a revisar de inmediato, sin esperar la frecuencia programada)
A37: Disparador | B37: Acción inmediata exigida
A38: Sismo sentido en la instalación | B38: Inspección estructural y de estantería antes de reanudar la operación; no se reingresa personal sin concepto.
A39: Incendio o conato, por pequeño que sea | B39: Investigación de causa, revisión de la carga de fuego y verificación integral del sistema de protección.
A40: Impacto significativo contra una estantería | B40: Descarga inmediata del módulo afectado, evaluación del daño (verde / ámbar / rojo) y reparación con repuesto original.
A41: Accidente grave, fatalidad o casi-accidente de alto potencial | B41: Investigación de causa raíz y recalificación de todos los riesgos de la misma familia.
A42: Inundación o vendaval en la zona | B42: Revisión de cubierta, drenajes, instalaciones eléctricas y producto almacenado en piso.
A43: Cambio de layout, de sistema de almacenamiento o de altura de almacenamiento | B43: Recálculo estructural, revisión del diseño de protección contra incendio y actualización de planos y placas de carga.
A44: Cambio del portafolio de producto (nuevos plásticos, aerosoles, litio, químicos) | B44: Reclasificación de la mercancía y validación del sistema de rociadores y de la segregación.
A45: Ingreso de un nuevo tipo de equipo de manipulación | B45: Actualización de flujos, ancho de pasillo, certificación de operadores y estudio de compatibilidad con el piso.
A46: Pico estacional o incremento sostenido del volumen | B46: Revisión de ocupación, capacidad, personal temporal, inducción y bloqueo de pasillos.
A47: Cambio de operador logístico, de contratista crítico o de transportista | B47: Homologación, auditoría inicial y revisión de responsabilidades.
A48: Cambio normativo o nueva exigencia de la aseguradora o del cliente | B48: Actualización de la matriz legal y cierre de las nuevas recomendaciones.
A49: Siniestro relevante en otra instalación de la compañía o del sector | B49: Autoevaluación del mismo escenario y verificación de los controles equivalentes.

Sheet 4. Plan de Inspección
A1: CALENDARIO DE INSPECCIONES Y VERIFICACIONES DEL CEDI
A2: Consolida las frecuencias exigidas por norma y por criticidad. Regla: si la frecuencia calculada por el nivel de riesgo es mayor que la de la norma, prevalece la más exigente.
A4: POR TURNO / DIARIA — verificación operativa
A5: # | B5: Actividad de inspección o verificación | C5: Elemento o sistema | D5: Responsable | E5: Norma o referencia | F5: Registro que se genera | G5: Riesgos (ID) | H5: Última ejecución | I5: Próxima programada | J5: Estado
A6: 1 | B6: Inspección preoperacional de cada equipo de manipulación antes de usarlo, con bloqueo del equipo ante hallazgo crítico | C6: Montacargas y demás MHE | D6: Operador / Supervisor | E6: OSHA 1910.178(q)(7) | F6: Formato preoperacional firmado | G6: E-02, E-03, E-09
A7: 2 | B7: Ronda de orden y aseo: pasillos, salidas de evacuación, extintores, hidrantes y tableros libres de obstrucción | C7: Toda la instalación | D7: Supervisor de turno | E7: NFPA 101 / NTC 1700 | F7: Ronda 5S con hallazgos | G7: C-03, F-04, K-02
A8: 3 | B8: Aseguramiento del vehículo en muelle: calzo o dock lock, semáforo y control de llaves en cada operación | C8: Muelles | D8: Supervisor de muelles | E8: OSHA 1910.178(k) | F8: Checklist de muelle | G8: D-01, D-08
A9: 4 | B9: Reporte inmediato de cualquier daño a estantería por parte de cualquier trabajador | C9: Estantería | D9: Todo el personal / PRRS | E9: EN 15635 §9 | F9: Tarjeta o reporte de daño | G9: B-02
A10: 5 | B10: Monitoreo y registro de temperatura de cámaras y muelles refrigerados; atención de alarmas | C10: Cadena de frío | D10: Calidad / Mantenimiento | E10: BPM / HACCP / GDP | F10: Registro continuo de temperatura | G10: L-01
A11: 6 | B11: Inspección de estibas en recibo y antes de ubicar en rack; retiro de estibas averiadas | C11: Estibas / unidad de carga | D11: Coordinador de recibo | E11: EN 15635 §8 | F11: Registro de rechazo | G11: B-10
A12: 7 | B12: Conteos cíclicos de referencias clase A y análisis de diferencias | C12: Inventario | D12: Control de inventarios | E12: Buena práctica | F12: Reporte ERI | G12: L-07, I-01
A13: 8 | B13: Control de acceso, requisas, bitácora de portería y control de sellos | C13: Seguridad física | D13: Seguridad física | E13: BASC / OEA | F13: Bitácora de portería y de sellos | G13: I-03, I-06
A14: 9 | B14: Revisión del nivel de ocupación, producto en piso y bloqueo de pasillos | C14: Capacidad | D14: Jefe de CEDI | E14: Política interna | F14: Reporte de ocupación del WMS | G14: C-01, C-03
A15: 10 | B15: Verificación de rumas y apilamiento en bloque (altura, estabilidad, demarcación) | C15: Almacenamiento en piso | D15: Supervisor de turno | E15: NFPA 230 | F15: Ronda de piso | G15: B-09
A17: SEMANAL
A18: # | B18: Actividad de inspección o verificación | C18: Elemento o sistema | D18: Responsable | E18: Norma o referencia | F18: Registro que se genera | G18: Riesgos (ID) | H18: Última ejecución | I18: Próxima programada | J18: Estado
A19: 1 | B19: Inspección visual de estantería por el PRRS con clasificación verde / ámbar / rojo y bloqueo de módulos rojos | C19: Estantería | D19: PRRS | E19: EN 15635 §9 | F19: Formato de inspección por módulo | G19: B-01, B-02, B-04
A20: 2 | B20: Arranque semanal de la bomba contra incendio sin flujo y verificación de presiones | C20: Protección contra incendio | D20: Mantenimiento | E20: NFPA 25 | F20: Registro de arranque | G20: F-02
A21: 3 | B21: Verificación de válvulas de control del sistema de rociadores abiertas y aseguradas | C21: Rociadores | D21: Mantenimiento / HSE | E21: NFPA 25 | F21: Checklist de válvulas | G21: F-01
A22: 4 | B22: Revisión del patio de estibas y de residuos: separación del edificio, altura de rumas y evacuación | C22: Carga de fuego | D22: HSE / Servicios generales | E22: NFPA 230 / FM DS 8-24 | F22: Ronda de carga de fuego | G22: F-09
A23: 5 | B23: Revisión de indicadores semanales: ocupación, averías, cumplimiento de citas, ERI, accidentalidad | C23: Gestión | D23: Jefe de CEDI | E23: ISO 9001 | F23: Tablero de indicadores | G23: M-05, D-06, L-08
A24: 6 | B24: Reporte de producto próximo a vencer y verificación de FEFO | C24: Inventario / calidad | D24: Calidad | E24: BPM | F24: Reporte de vencimientos | G24: L-04
A26: MENSUAL
A27: # | B27: Actividad de inspección o verificación | C27: Elemento o sistema | D27: Responsable | E27: Norma o referencia | F27: Registro que se genera | G27: Riesgos (ID) | H27: Última ejecución | I27: Próxima programada | J27: Estado
A28: 1 | B28: Inspección de extintores: presión, sello, señalización, acceso y fecha de vencimiento | C28: Extintores | D28: HSE / Brigada | E28: NFPA 10 / NTC 2885 | F28: Tarjeta de inspección | G28: F-04
A29: 2 | B29: Prueba funcional (30 segundos) de la iluminación de emergencia | C29: Evacuación | D29: Mantenimiento | E29: NFPA 101 | F29: Registro de prueba | G29: F-12
A30: 3 | B30: Lectura de manómetros y revisión del panel de detección y alarma | C30: Protección contra incendio | D30: Mantenimiento | E30: NFPA 25 / NFPA 72 | F30: Registro mensual | G30: F-01, F-03
A31: 4 | B31: Auditoría de comportamiento en la interacción montacargas-peatón y de velocidades | C31: Seguridad operativa | D31: HSE | E31: SG-SST | F31: Informe de observación | G31: E-01, E-09
A32: 5 | B32: Inspección de la sala de carga de baterías y de la zona de litio: ventilación, ducha, lavaojos y kit | C32: Baterías | D32: Mantenimiento / HSE | E32: NFPA 855 / OSHA 1910.178(g) | F32: Checklist de sala de baterías | G32: E-05, E-06
A33: 6 | B33: Revisión de instalaciones eléctricas provisionales, extensiones y tableros cerrados y rotulados | C33: Instalación eléctrica | D33: Mantenimiento | E33: RETIE / NFPA 70B | F33: Reporte de hallazgos | G33: F-08, H-01
A34: 7 | B34: Verificación de la matriz de operadores certificados, contratistas y personal en misión | C34: Personas | D34: HSE / Talento humano | E34: SG-SST / OSHA 1910.178(l) | F34: Matriz de autorización | G34: E-04, K-06, N-01
A35: 8 | B35: Informe del programa de control de plagas (MIP) y análisis de tendencia de capturas | C35: Sanidad | D35: Calidad | E35: BPM / Resolución 2674 de 2013 | F35: Informe MIP | G35: L-02
A36: 9 | B36: Prueba de la planta eléctrica con carga y verificación de combustible y baterías de arranque | C36: Energía de respaldo | D36: Mantenimiento | E36: NFPA 110 | F36: Registro de prueba | G36: H-03
A37: 10 | B37: Inspección de niveladores, rampas, puertas y abrigos de muelle | C37: Muelles | D37: Mantenimiento | E37: Manual del fabricante | F37: Checklist de muelle | G37: D-03, D-04
A38: 11 | B38: Comparación del valor del inventario contra el valor asegurado y las cláusulas de la póliza | C38: Financiero | D38: Finanzas | E38: Condiciones de la póliza | F38: Reporte de valorización | G38: C-04, O-02
A39: 12 | B39: Verificación de botiquines, camillas, DEA y dotación de emergencia por turno | C39: Emergencias | D39: HSE / Brigada | E39: Resolución 0705 de 2007 | F39: Inventario de botiquines | G39: K-09, F-11
... A44: 17 | B44: Verificación de pasadores de seguridad de vigas y de protectores de columna (muestreo por zona) | C44: Estantería | D44: PRRS | E44: EN 15635 | F44: Checklist por zona | G44: B-04, B-05
A46: TRIMESTRAL
A47: # | B47: Actividad de inspección o verificación | C47: Elemento o sistema | D47: Responsable | E47: Norma o referencia | F47: Registro que se genera | G47: Riesgos (ID) | H47: Última ejecución | I47: Próxima programada | J47: Estado
A48: 1 | B48: Prueba de dispositivos de alarma de flujo de agua y de supervisión de válvulas | C48: Protección contra incendio | D48: Mantenimiento | E48: NFPA 25 | F48: Informe de prueba | G48: F-01, F-03
A49: 2 | B49: Inspección de gabinetes contra incendio, mangueras e hidrantes internos y externos | C49: Red hidráulica | D49: Mantenimiento / Brigada | E49: NFPA 25 / NFPA 14 | F49: Registro de inspección | G49: F-05
A50: 3 | B50: Inspección de sellos cortafuego, puertas cortafuego y continuidad de la sectorización | C50: Sectorización | D50: Mantenimiento | E50: NFPA 80 / NFPA 221 | F50: Checklist de sectorización | G50: A-04
A51: 4 | B51: Limpieza y revisión de cubierta, canales, bajantes y tragantes | C51: Cubierta | D51: Mantenimiento | E51: Manual del fabricante | F51: Orden de trabajo con fotos | G51: A-02, G-06
A52: 5 | B52: Inspección de mezanine, barandas, rodapiés, compuertas y escaleras | C52: Entrepisos | D52: Mantenimiento / HSE | E52: NSR-10 / Resolución 1409 de 2012 | F52: Checklist de entrepiso | G52: B-08
A53: 6 | B53: Entrenamiento y verificación de cobertura de la brigada de emergencia por turno | C53: Emergencias | D53: HSE | E53: Decreto 1072 de 2015 / NFPA 600 | F53: Registro de entrenamiento | G53: F-11
A54: 7 | B54: Inspección de EPP de trabajo en alturas: arneses, eslingas y puntos de anclaje | C54: SST | D54: HSE | E54: Resolución 1409 de 2012 | F54: Formato de inspección de EPP | G54: K-03, E-08
A55: 8 | B55: Auditoría de seguridad física: hurto interno, sellos, accesos y análisis de pérdida desconocida | C55: Seguridad física | D55: Seguridad física | E55: ISO 28000 / BASC | F55: Informe de auditoría | G55: I-01, I-03, I-06
A56: 9 | B56: Recorrido perimetral: cerramiento, iluminación de seguridad, sensores y franja libre | C56: Perímetro | D56: Seguridad física | E56: BASC | F56: Informe de recorrido | G56: I-07
A57: 10 | B57: Inspección de mallas antiderrumbe, topes y protecciones de estantería | C57: Estantería | D57: PRRS / Mantenimiento | E57: EN 15635 | F57: Checklist de protecciones | G57: B-11, B-05
A58: 11 | B58: Prueba de restauración de respaldos de información y revisión de accesos | C58: TI | D58: TI | E58: ISO 27001 | F58: Acta de restauración | G58: J-02, J-04
A59: 12 | B59: Evaluación de proveedores críticos, 3PL y transportistas | C59: Terceros | D59: Compras / Jefe de CEDI | E59: ISO 9001 | F59: Evaluación de proveedores | G59: N-03, N-04
... A61: 14 | B61: Inspección visual de tableros eléctricos, cuartos técnicos y subestación | C61: Instalación eléctrica | D61: Mantenimiento | E61: RETIE / NFPA 70B | F61: Checklist eléctrico | G61: H-01, H-02
A63: SEMESTRAL
A64: # | B64: Actividad de inspección o verificación | C64: Elemento o sistema | D64: Responsable | E64: Norma o referencia | F64: Registro que se genera | G64: Riesgos (ID) | H64: Última ejecución | I64: Próxima programada | J64: Estado
A65: 1 | B65: Simulacro de evacuación (idealmente uno por turno al año) con evaluación y plan de mejora | C65: Emergencias | D65: HSE / Brigada | E65: Decreto 1072 de 2015 / NTC 1700 | F65: Acta de simulacro | G65: F-10
A66: 2 | B66: Medición de niveles de iluminación en bodega, muelles y patio | C66: Condiciones de trabajo | D66: HSE / Mantenimiento | E66: RETILAP / ISO 8995 | F66: Informe de medición | G66: D-10
A67: 3 | B67: Prueba del procedimiento manual de contingencia ante caída del WMS | C67: TI / operación | D67: TI / Jefe de CEDI | E67: ISO 22301 | F67: Acta de prueba | G67: J-01
A68: 4 | B68: Mantenimiento preventivo de niveladores, puertas y equipos de muelle | C68: Muelles | D68: Mantenimiento | E68: Manual del fabricante | F68: Orden de trabajo | G68: D-03
A69: 5 | B69: Inspección del piso industrial: juntas, fisuras, planitud y estado bajo placas base | C69: Piso | D69: Mantenimiento / Ingeniería | E69: EN 15620 / ACI 302 | F69: Informe de piso | G69: A-03
A70: 6 | B70: Revisión de layout, flujos, slotting y análisis de recorridos | C70: Operación | D70: Ingeniería / Jefe de CEDI | E70: Buena práctica | F70: Plano actualizado y análisis ABC | G70: M-02, C-05
A71: 7 | B71: Actualización del análisis de amenaza de seguridad de la zona | C71: Seguridad física | D71: Seguridad física | E71: ISO 28000 | F71: Estudio de amenaza | G71: I-02
A72: 8 | B72: Análisis de vulnerabilidades de TI y campaña de concientización | C72: Ciberseguridad | D72: TI | E72: ISO 27001 / NIST CSF | F72: Informe de vulnerabilidades | G72: J-02
A73: 9 | B73: Preparación pre-temporada de lluvias y vientos: drenajes, cubierta, patio y producto en piso | C73: Riesgos naturales | D73: Mantenimiento / HSE | E73: Plan de temporada | F73: Checklist pre-temporada | G73: G-04, G-05, G-06, A-02
A74: 10 | B74: Seguimiento al programa de ergonomía y a la vigilancia epidemiológica | C74: SST | D74: HSE / Medicina laboral | E74: ISO 11228 / SG-SST | F74: Informe del programa | G74: K-01
A75: 11 | B75: Site survey de cobertura de radiofrecuencia por zonas | C75: TI | D75: TI | E75: Buena práctica | F75: Mapa de calor de cobertura | G75: J-03
A76: 12 | B76: Medición de estrés térmico y verificación de rotación en cuartos fríos | C76: SST | D76: HSE | E76: ACGIH TLV | F76: Informe de medición | G76: K-04
A78: ANUAL
A79: # | B79: Actividad de inspección o verificación | C79: Elemento o sistema | D79: Responsable | E79: Norma o referencia | F79: Registro que se genera | G79: Riesgos (ID) | H79: Última ejecución | I79: Próxima programada | J79: Estado
A80: 1 | B80: INSPECCIÓN EXPERTA DE ESTANTERÍA por tercero técnicamente competente, con informe y plan de reparación | C80: Estantería | D80: Tercero externo / PRRS | E80: EN 15635 §9.4 | F80: Informe de inspección experta | G80: B-01, B-02, B-03, B-12
A81: 2 | B81: Prueba anual con flujo de la bomba contra incendio contra su curva de diseño | C81: Protección contra incendio | D81: Mantenimiento / tercero | E81: NFPA 25 / NFPA 20 | F81: Informe de prueba de flujo | G81: F-02
A82: 3 | B82: Prueba de autonomía (90 minutos) de la iluminación de emergencia | C82: Evacuación | D82: Mantenimiento | E82: NFPA 101 | F82: Registro de prueba | G82: F-12
A83: 4 | B83: Mantenimiento y recarga de extintores | C83: Extintores | D83: Proveedor certificado | E83: NFPA 10 / NTC 2885 | F83: Certificado de recarga | G83: F-04
A84: 5 | B84: Certificación anual del sistema de detección y alarma | C84: Detección | D84: Tercero certificado | E84: NFPA 72 | F84: Certificado de funcionamiento | G84: F-03
A85: 6 | B85: Termografía de tableros eléctricos con carga y cierre de anomalías | C85: Instalación eléctrica | D85: Tercero / Mantenimiento | E85: NFPA 70B / NETA | F85: Informe termográfico | G85: H-01
A86: 7 | B86: Mantenimiento de subestación y análisis de aceite dieléctrico | C86: Subestación | D86: Tercero certificado | E86: RETIE / IEEE C57 | F86: Informe de mantenimiento | G86: H-02
A87: 8 | B87: Medición de resistencia de puesta a tierra y revisión del sistema de protección contra rayos | C87: Puesta a tierra / SPT | D87: Tercero certificado | E87: RETIE / NTC 4552 / NFPA 780 | F87: Certificado de medición | G87: G-07
A88: 9 | B88: Calibración de sensores y registradores de temperatura | C88: Cadena de frío | D88: Laboratorio acreditado | E88: BPM / GDP | F88: Certificados de calibración | G88: L-01
A89: 10 | B89: Simulacro de trazabilidad y de retiro de producto (recall) con medición de tiempos | C89: Calidad | D89: Calidad | E89: ISO 22000 / BPM | F89: Acta de simulacro de recall | G89: L-10
A90: 11 | B90: Prueba del plan de continuidad del negocio y actualización del análisis de impacto (BIA) | C90: Continuidad | D90: Gerencia | E90: ISO 22301 | F90: Acta de prueba del BCP | G90: O-04, O-05
A91: 12 | B91: Autoevaluación de estándares mínimos del SG-SST y formulación del plan de trabajo anual | C91: Cumplimiento SST | D91: HSE | E91: Resolución 0312 de 2019 | F91: Autoevaluación y plan anual | G91: O-03
... A100: 21 | B100: Evaluación de dispositivos de retención de carga en niveles altos (riesgo sísmico) | C100: Estantería / sismo | D100: PRRS / HSE | E100: FEM 10.2.08 | F100: Checklist sísmico | G100: G-02
A102: CADA 3 A 5 AÑOS (plurianual)
A103: # | B103: Actividad de inspección o verificación | C103: Elemento o sistema | D103: Responsable | E103: Norma o referencia | F103: Registro que se genera | G103: Riesgos (ID) | H103: Última ejecución | I103: Próxima programada | J103: Estado
A104: 1 | B104: Inspección interna de la tubería del sistema de rociadores (obstrucciones) | C104: Rociadores | D104: Tercero certificado | E104: NFPA 25 (5 años) | F104: Informe de inspección interna | G104: F-01
A105: 2 | B105: Prueba de presión o reemplazo de mangueras contra incendio | C105: Red hidráulica | D105: Tercero certificado | E105: NFPA 1962 (5 años) | F105: Certificado de prueba | G105: F-05
A106: 3 | B106: Prueba hidrostática de extintores según el tipo de agente | C106: Extintores | D106: Proveedor certificado | E106: NFPA 10 (5 a 12 años) | F106: Certificado hidrostático | G106: F-04
A107: 4 | B107: Evaluación de vulnerabilidad estructural del edificio | C107: Estructura | D107: Ingeniero estructural | E107: NSR-10 / ASCE 41 (1 a 3 años y tras evento) | F107: Informe estructural | G107: A-01, G-01
A108: 5 | B108: Recertificación de operadores de equipos de manipulación | C108: MHE | D108: HSE / Talento humano | E108: OSHA 1910.178(l)(4)(iii) (3 años) | F108: Certificados vigentes | G108: E-04
A109: 6 | B109: Prueba de intrusión (pentest) sobre los sistemas operativos y de gestión | C109: TI | D109: Tercero especializado | E109: ISO 27001 (1 a 2 años) | F109: Informe de pentest | G109: J-02
A110: 7 | B110: Estudio de capacidad del piso ante cambio de sistema de almacenamiento o de equipos | C110: Piso / estructura | D110: Ingeniería | E110: EN 15620 (ante cambio) | F110: Estudio técnico | G110: A-03, B-06
A112: POR EVENTO / DISPARADOR — no esperan la programación
A113: # | B113: Actividad de inspección o verificación | C113: Elemento o sistema | D113: Responsable | E113: Norma o referencia | F113: Registro que se genera | G113: Riesgos (ID) | H113: Última ejecución | I113: Próxima programada | J113: Estado
A114: 1 | B114: Tras sismo sentido: inspección estructural y de estantería antes de reingresar personal | C114: Estructura y estantería | D114: Ingeniería / PRRS | E114: NSR-10 / EN 15635 | F114: Acta de inspección post-evento | G114: G-01, G-03
A115: 2 | B115: Tras impacto contra estantería: descarga y evaluación del módulo (verde / ámbar / rojo) | C115: Estantería | D115: PRRS | E115: EN 15635 §9 | F115: Reporte de daño y reparación | G115: B-02
A116: 3 | B116: Tras incendio o conato: investigación, revisión de carga de fuego y del sistema de protección | C116: Incendio | D116: HSE | E116: NFPA 1600 | F116: Informe de investigación | G116: F-01, C-02
A117: 4 | B117: Tras accidente grave o casi-accidente de alto potencial: causa raíz y recalificación de riesgos afines | C117: SST | D117: HSE | E117: ISO 45001 / Resolución 1401 de 2007 | F117: Informe de investigación | G117: O-07
A118: 5 | B118: Ante cambio de layout, de altura o de sistema de almacenamiento: recálculo y actualización de planos | C118: Almacenamiento | D118: Ingeniería / PRRS | E118: EN 15629 / NFPA 13 | F118: Aval técnico y planos as-built | G118: B-06, A-06
A119: 6 | B119: Ante cambio de portafolio: reclasificación de mercancía y revisión de segregación y rociadores | C119: Producto / incendio | D119: HSE / Calidad | E119: NFPA 13 / NFPA 400 | F119: Estudio actualizado | G119: C-02, L-03
A120: 7 | B120: Antes de temporada alta: revisión de capacidad, personal, inducción y bloqueo de pasillos | C120: Operación | D120: Jefe de CEDI | E120: Plan de temporada | F120: Plan de temporada aprobado | G120: C-06, K-06
A121: 8 | B121: Ante inundación o vendaval: revisión de cubierta, drenajes, instalación eléctrica y producto en piso | C121: Riesgos naturales | D121: Mantenimiento | E121: Protocolo de temporada | F121: Acta de inspección | G121: G-04, G-05

Sheet 5. Plan de Acción
A1: PLAN DE ACCIÓN — CIERRE DE HALLAZGOS
A2: Todo hallazgo 'No' o 'Parcial' de la matriz se traslada aquí. El plazo máximo depende del nivel de riesgo: Extremo ≤ 15 días · Alto ≤ 30 días · Medio ≤ 90 días.
A4: N° | B4: ID riesgo | C4: Hallazgo detectado | D4: Nivel | E4: Acción correctiva, preventiva o de mejora | F4: Tipo de acción | G4: Responsable | H4: Fecha compromiso | I4: Fecha de cierre | J4: % avance | K4: Verificación de eficacia (cómo se comprueba) | L4: Estado
A5: 1
A6: 2
A7: 3
A8: 4
A9: 5
A10: 6
A11: 7
A12: 8
A13: 9
A14: 10
A15: 11
A16: 12
... A44: 40

Sheet 6. Tablero
B1: TABLERO DE RIESGO DEL CENTRO DE DISTRIBUCIÓN
B2: Se actualiza automáticamente a partir de la hoja '2. Matriz de Riesgos'.
A4: PERFIL DE RIESGO POR NIVEL
B5: Nivel de riesgo | C5: Cantidad | D5: % del total | E5: Frecuencia mínima de revisión
B6: Extremo | C6: =COUNTIF('2. Matriz de Riesgos'!$L$5:$L$122,"Extremo") -> 5 | D6: =IFERROR(C6/$C$11,0) -> 0.042372881 | E6: Diaria/por turno + inspección semanal
B7: Alto | C7: =COUNTIF('2. Matriz de Riesgos'!$L$5:$L$122,"Alto") -> 75 | D7: =IFERROR(C7/$C$11,0) -> 0.63559322 | E7: Semanal + inspección mensual
B8: Medio | C8: =COUNTIF('2. Matriz de Riesgos'!$L$5:$L$122,"Medio") -> 38 | D8: =IFERROR(C8/$C$11,0) -> 0.3220339 | E8: Mensual o trimestral
B9: Bajo | C9: =COUNTIF('2. Matriz de Riesgos'!$L$5:$L$122,"Bajo") -> 0 | D9: =IFERROR(C9/$C$11,0) -> 0 | E9: Semestral
B10: Muy bajo | C10: =COUNTIF('2. Matriz de Riesgos'!$L$5:$L$122,"Muy bajo") -> 0 | D10: =IFERROR(C10/$C$11,0) -> 0 | E10: Anual
B11: Riesgos evaluados | C11: =SUM(C6:C10) -> 118
A13: ESTADO DE CUMPLIMIENTO DEL CHECKLIST
B14: Resultado de la verificación | C14: Cantidad | D14: %
B15: Sí | C15: =COUNTIF('2. Matriz de Riesgos'!$Q$5:$Q$122,"Sí") -> 0 | D15: =IFERROR(C15/COUNTA('2. Matriz de Riesgos'!$Q$5:$Q$122),0) -> 0
B16: Parcial | C16: =COUNTIF('2. Matriz de Riesgos'!$Q$5:$Q$122,"Parcial") -> 0 | D16: =IFERROR(C16/COUNTA('2. Matriz de Riesgos'!$Q$5:$Q$122),0) -> 0
B17: No | C17: =COUNTIF('2. Matriz de Riesgos'!$Q$5:$Q$122,"No") -> 0 | D17: =IFERROR(C17/COUNTA('2. Matriz de Riesgos'!$Q$5:$Q$122),0) -> 0
B18: N.A. | C18: =COUNTIF('2. Matriz de Riesgos'!$Q$5:$Q$122,"N.A.") -> 0 | D18: =IFERROR(C18/COUNTA('2. Matriz de Riesgos'!$Q$5:$Q$122),0) -> 0
B19: Sin evaluar | C19: =COUNTIF('2. Matriz de Riesgos'!$Q$5:$Q$122,"Sin evaluar") -> 0 | D19: =IFERROR(C19/COUNTA('2. Matriz de Riesgos'!$Q$5:$Q$122),0) -> 0
B20: Índice de cumplimiento = Sí / (Sí + Parcial + No) | C20: =IFERROR(C15/(C15+C16+C17),0) -> 0
A22: PERFIL DE RIESGO POR CATEGORÍA
B23: Categoría de riesgo | C23: Extremo | D23: Alto | E23: Medio | F23: Bajo | G23: Muy bajo | H23: Total | I23: Riesgos que exigen verificación semanal o más frecuente
B24: A. Infraestructura y edificio | C24: =COUNTIFS('2. Matriz de Riesgos'!$B$5:$B$122,$B24,'2. Matriz de Riesgos'!$L$5:$L$122,"Extremo") -> 1 | D24: =COUNTIFS('2. Matriz de Riesgos'!$B$5:$B$122,$B24,'2. Matriz de Riesgos'!$L$5:$L$122,"Alto") -> 3 | E24: =COUNTIFS('2. Matriz de Riesgos'!$B$5:$B$122,$B24,'2. Matriz de Riesgos'!$L$5:$L$122,"Medio") -> 2 | F24: =COUNTIFS('2. Matriz de Riesgos'!$B$5:$B$122,$B24,'2. Matriz de Riesgos'!$L$5:$L$122,"Bajo") -> 0 | G24: =COUNTIFS('2. Matriz de Riesgos'!$B$5:$B$122,$B24,'2. Matriz de Riesgos'!$L$5:$L$122,"Muy bajo") -> 0 | H24: =SUM(C24:G24) -> 6 | I24: =C24+D24 -> 4
B25: B. Estantería y sistemas de almacenamiento | C25: =COUNTIFS('2. Matriz de Riesgos'!$B$5:$B$122,$B25,'2. Matriz de Riesgos'!$L$5:$L$122,"Extremo") -> 2 | D25: =COUNTIFS('2. Matriz de Riesgos'!$B$5:$B$122,$B25,'2. Matriz de Riesgos'!$L$5:$L$122,"Alto") -> 9 | E25: =COUNTIFS('2. Matriz de Riesgos'!$B$5:$B$122,$B25,'2. Matriz de Riesgos'!$L$5:$L$122,"Medio") -> 1 | F25: =COUNTIFS('2. Matriz de Riesgos'!$B$5:$B$122,$B25,'2. Matriz de Riesgos'!$L$5:$L$122,"Bajo") -> 0 | G25: =COUNTIFS('2. Matriz de Riesgos'!$B$5:$B$122,$B25,'2. Matriz de Riesgos'!$L$5:$L$122,"Muy bajo") -> 0 | H25: =SUM(C25:G25) -> 12 | I25: =C25+D25 -> 11
B26: C. Volumen de inventario y ocupación | C26: =COUNTIFS('2. Matriz de Riesgos'!$B$5:$B$122,$B26,'2. Matriz de Riesgos'!$L$5:$L$122,"Extremo") -> 1 | D26: =COUNTIFS('2. Matriz de Riesgos'!$B$5:$B$122,$B26,'2. Matriz de Riesgos'!$L$5:$L$122,"Alto") -> 4 | E26: =COUNTIFS('2. Matriz de Riesgos'!$B$5:$B$122,$B26,'2. Matriz de Riesgos'!$L$5:$L$122,"Medio") -> 1 | F26: =COUNTIFS('2. Matriz de Riesgos'!$B$5:$B$122,$B26,'2. Matriz de Riesgos'!$L$5:$L$122,"Bajo") -> 0 | G26: =COUNTIFS('2. Matriz de Riesgos'!$B$5:$B$122,$B26,'2. Matriz de Riesgos'!$L$5:$L$122,"Muy bajo") -> 0 | H26: =SUM(C26:G26) -> 6 | I26: =C26+D26 -> 5
B27: D. Muelles y patio de maniobras | C27: =COUNTIFS('2. Matriz de Riesgos'!$B$5:$B$122,$B27,'2. Matriz de Riesgos'!$L$5:$L$122,"Extremo") -> 0 | D27: =COUNTIFS('2. Matriz de Riesgos'!$B$5:$B$122,$B27,'2. Matriz de Riesgos'!$L$5:$L$122,"Alto") -> 6 | E27: =COUNTIFS('2. Matriz de Riesgos'!$B$5:$B$122,$B27,'2. Matriz de Riesgos'!$L$5:$L$122,"Medio") -> 4 | F27: =COUNTIFS('2. Matriz de Riesgos'!$B$5:$B$122,$B27,'2. Matriz de Riesgos'!$L$5:$L$122,"Bajo") -> 0 | G27: =COUNTIFS('2. Matriz de Riesgos'!$B$5:$B$122,$B27,'2. Matriz de Riesgos'!$L$5:$L$122,"Muy bajo") -> 0 | H27: =SUM(C27:G27) -> 10 | I27: =C27+D27 -> 6
B28: E. Equipos de manipulación (MHE) | C28: =COUNTIFS('2. Matriz de Riesgos'!$B$5:$B$122,$B28,'2. Matriz de Riesgos'!$L$5:$L$122,"Extremo") -> 1 | D28: =COUNTIFS('2. Matriz de Riesgos'!$B$5:$B$122,$B28,'2. Matriz de Riesgos'!$L$5:$L$122,"Alto") -> 7 | E28: =COUNTIFS('2. Matriz de Riesgos'!$B$5:$B$122,$B28,'2. Matriz de Riesgos'!$L$5:$L$122,"Medio") -> 2 | F28: =COUNTIFS('2. Matriz de Riesgos'!$B$5:$B$122,$B28,'2. Matriz de Riesgos'!$L$5:$L$122,"Bajo") -> 0 | G28: =COUNTIFS('2. Matriz de Riesgos'!$B$5:$B$122,$B28,'2. Matriz de Riesgos'!$L$5:$L$122,"Muy bajo") -> 0 | H28: =SUM(C28:G28) -> 10 | I28: =C28+D28 -> 8
B29: F. Incendio y protección contra incendio | C29: =COUNTIFS('2. Matriz de Riesgos'!$B$5:$B$122,$B29,'2. Matriz de Riesgos'!$L$5:$L$122,"Extremo") -> 0 | D29: =COUNTIFS('2. Matriz de Riesgos'!$B$5:$B$122,$B29,'2. Matriz de Riesgos'!$L$5:$L$122,"Alto") -> 12 | E29: =COUNTIFS('2. Matriz de Riesgos'!$B$5:$B$122,$B29,'2. Matriz de Riesgos'!$L$5:$L$122,"Medio") -> 1 | F29: =COUNTIFS('2. Matriz de Riesgos'!$B$5:$B$122,$B29,'2. Matriz de Riesgos'!$L$5:$L$122,"Bajo") -> 0 | G29: =COUNTIFS('2. Matriz de Riesgos'!$B$5:$B$122,$B29,'2. Matriz de Riesgos'!$L$5:$L$122,"Muy bajo") -> 0 | H29: =SUM(C29:G29) -> 13 | I29: =C29+D29 -> 12
B30: G. Riesgos naturales y del entorno | C30: =COUNTIFS('2. Matriz de Riesgos'!$B$5:$B$122,$B30,'2. Matriz de Riesgos'!$L$5:$L$122,"Extremo") -> 0 | D30: =COUNTIFS('2. Matriz de Riesgos'!$B$5:$B$122,$B30,'2. Matriz de Riesgos'!$L$5:$L$122,"Alto") -> 4 | E30: =COUNTIFS('2. Matriz de Riesgos'!$B$5:$B$122,$B30,'2. Matriz de Riesgos'!$L$5:$L$122,"Medio") -> 5 | F30: =COUNTIFS('2. Matriz de Riesgos'!$B$5:$B$122,$B30,'2. Matriz de Riesgos'!$L$5:$L$122,"Bajo") -> 0 | G30: =COUNTIFS('2. Matriz de Riesgos'!$B$5:$B$122,$B30,'2. Matriz de Riesgos'!$L$5:$L$122,"Muy bajo") -> 0 | H30: =SUM(C30:G30) -> 9 | I30: =C30+D30 -> 4
B31: H. Eléctrico y servicios industriales | C31: =COUNTIFS('2. Matriz de Riesgos'!$B$5:$B$122,$B31,'2. Matriz de Riesgos'!$L$5:$L$122,"Extremo") -> 0 | D31: =COUNTIFS('2. Matriz de Riesgos'!$B$5:$B$122,$B31,'2. Matriz de Riesgos'!$L$5:$L$122,"Alto") -> 2 | E31: =COUNTIFS('2. Matriz de Riesgos'!$B$5:$B$122,$B31,'2. Matriz de Riesgos'!$L$5:$L$122,"Medio") -> 3 | F31: =COUNTIFS('2. Matriz de Riesgos'!$B$5:$B$122,$B31,'2. Matriz de Riesgos'!$L$5:$L$122,"Bajo") -> 0 | G31: =COUNTIFS('2. Matriz de Riesgos'!$B$5:$B$122,$B31,'2. Matriz de Riesgos'!$L$5:$L$122,"Muy bajo") -> 0 | H31: =SUM(C31:G31) -> 5 | I31: =C31+D31 -> 2
B32: I. Seguridad física y protección de la carga | C32: =COUNTIFS('2. Matriz de Riesgos'!$B$5:$B$122,$B32,'2. Matriz de Riesgos'!$L$5:$L$122,"Extremo") -> 0 | D32: =COUNTIFS('2. Matriz de Riesgos'!$B$5:$B$122,$B32,'2. Matriz de Riesgos'!$L$5:$L$122,"Alto") -> 5 | E32: =COUNTIFS('2. Matriz de Riesgos'!$B$5:$B$122,$B32,'2. Matriz de Riesgos'!$L$5:$L$122,"Medio") -> 3 | F32: =COUNTIFS('2. Matriz de Riesgos'!$B$5:$B$122,$B32,'2. Matriz de Riesgos'!$L$5:$L$122,"Bajo") -> 0 | G32: =COUNTIFS('2. Matriz de Riesgos'!$B$5:$B$122,$B32,'2. Matriz de Riesgos'!$L$5:$L$122,"Muy bajo") -> 0 | H32: =SUM(C32:G32) -> 8 | I32: =C32+D32 -> 5
B33: J. Tecnología de información | C33: =COUNTIFS('2. Matriz de Riesgos'!$B$5:$B$122,$B33,'2. Matriz de Riesgos'!$L$5:$L$122,"Extremo") -> 0 | D33: =COUNTIFS('2. Matriz de Riesgos'!$B$5:$B$122,$B33,'2. Matriz de Riesgos'!$L$5:$L$122,"Alto") -> 3 | E33: =COUNTIFS('2. Matriz de Riesgos'!$B$5:$B$122,$B33,'2. Matriz de Riesgos'!$L$5:$L$122,"Medio") -> 1 | F33: =COUNTIFS('2. Matriz de Riesgos'!$B$5:$B$122,$B33,'2. Matriz de Riesgos'!$L$5:$L$122,"Bajo") -> 0 | G33: =COUNTIFS('2. Matriz de Riesgos'!$B$5:$B$122,$B33,'2. Matriz de Riesgos'!$L$5:$L$122,"Muy bajo") -> 0 | H33: =SUM(C33:G33) -> 4 | I33: =C33+D33 -> 3
B34: K. Personas y seguridad y salud en el trabajo | C34: =COUNTIFS('2. Matriz de Riesgos'!$B$5:$B$122,$B34,'2. Matriz de Riesgos'!$L$5:$L$122,"Extremo") -> 0 | D34: =COUNTIFS('2. Matriz de Riesgos'!$B$5:$B$122,$B34,'2. Matriz de Riesgos'!$L$5:$L$122,"Alto") -> 5 | E34: =COUNTIFS('2. Matriz de Riesgos'!$B$5:$B$122,$B34,'2. Matriz de Riesgos'!$L$5:$L$122,"Medio") -> 4 | F34: =COUNTIFS('2. Matriz de Riesgos'!$B$5:$B$122,$B34,'2. Matriz de Riesgos'!$L$5:$L$122,"Bajo") -> 0 | G34: =COUNTIFS('2. Matriz de Riesgos'!$B$5:$B$122,$B34,'2. Matriz de Riesgos'!$L$5:$L$122,"Muy bajo") -> 0 | H34: =SUM(C34:G34) -> 9 | I34: =C34+D34 -> 5
B35: L. Producto, calidad y sanidad | C35: =COUNTIFS('2. Matriz de Riesgos'!$B$5:$B$122,$B35,'2. Matriz de Riesgos'!$L$5:$L$122,"Extremo") -> 0 | D35: =COUNTIFS('2. Matriz de Riesgos'!$B$5:$B$122,$B35,'2. Matriz de Riesgos'!$L$5:$L$122,"Alto") -> 7 | E35: =COUNTIFS('2. Matriz de Riesgos'!$B$5:$B$122,$B35,'2. Matriz de Riesgos'!$L$5:$L$122,"Medio") -> 3 | F35: =COUNTIFS('2. Matriz de Riesgos'!$B$5:$B$122,$B35,'2. Matriz de Riesgos'!$L$5:$L$122,"Bajo") -> 0 | G35: =COUNTIFS('2. Matriz de Riesgos'!$B$5:$B$122,$B35,'2. Matriz de Riesgos'!$L$5:$L$122,"Muy bajo") -> 0 | H35: =SUM(C35:G35) -> 10 | I35: =C35+D35 -> 7
... B38: O. Legal, financiero y continuidad | C38: =COUNTIFS('2. Matriz de Riesgos'!$B$5:$B$122,$B38,'2. Matriz de Riesgos'!$L$5:$L$122,"Extremo") -> 0 | D38: =COUNTIFS('2. Matriz de Riesgos'!$B$5:$B$122,$B38,'2. Matriz de Riesgos'!$L$5:$L$122,"Alto") -> 4 | E38: =COUNTIFS('2. Matriz de Riesgos'!$B$5:$B$122,$B38,'2. Matriz de Riesgos'!$L$5:$L$122,"Medio") -> 3 | F38: =COUNTIFS('2. Matriz de Riesgos'!$B$5:$B$122,$B38,'2. Matriz de Riesgos'!$L$5:$L$122,"Bajo") -> 0 | G38: =COUNTIFS('2. Matriz de Riesgos'!$B$5:$B$122,$B38,'2. Matriz de Riesgos'!$L$5:$L$122,"Muy bajo") -> 0 | H38: =SUM(C38:G38) -> 7 | I38: =C38+D38 -> 4
A40: INDICADORES QUE CONVIENE MONITOREAR (señales tempranas)
B41: Indicador | C41: Fórmula / unidad | E41: Frecuencia | G41: Meta de referencia
B42: Ocupación de posiciones de estiba | C42: Posiciones ocupadas / instaladas | E42: Diaria | G42: ≤ 85% promedio
B43: Daños en estantería detectados (rojo / ámbar) | C43: N° de módulos por color | E43: Semanal | G43: 0 rojos; ámbar en reparación ≤ 30 días
B44: Accidentalidad y casi-accidentes | C44: Frecuencia y severidad; N° de reportes | E44: Mensual | G44: Tendencia decreciente; reportes al alza (cultura)
B45: Impactos de montacargas registrados | C45: N° de impactos / 1.000 horas de operación | E45: Mensual | G45: Tendencia decreciente
B46: Cumplimiento del plan de mantenimiento preventivo | C46: OT ejecutadas / OT programadas | E46: Mensual | G46: ≥ 95%
B47: Cumplimiento del plan de inspecciones | C47: Inspecciones ejecutadas / programadas | E47: Mensual | G47: 100% en riesgos Extremo y Alto
B48: Exactitud de inventario (ERI) | C48: Ubicaciones correctas / ubicaciones contadas | E48: Semanal | G48: ≥ 99%
B49: Pérdida desconocida | C49: Valor de la pérdida / ventas o valor movilizado | E49: Mensual | G49: Según política; tendencia decreciente
B50: Averías y merma operativa | C50: Valor de averías / valor movilizado | E50: Semanal | G50: Tendencia decreciente
B51: Acciones vencidas del plan de acción | C51: N° de acciones vencidas | E51: Mensual | G51: 0 en riesgos Extremo y Alto
B52: Tiempo de permanencia del vehículo en el CEDI | C52: Horas promedio por vehículo | E52: Semanal | G52: Según acuerdo con transportistas
B53: Rotación y ausentismo del personal de bodega | C53: % | E53: Mensual | G53: Vigilar picos: preceden a la accidentalidad

Sheet 7. Referencias
B1: MARCO NORMATIVO Y ESTÁNDARES DE REFERENCIA
B2: Referencias usadas para definir los puntos de verificación y las frecuencias. Valide siempre la versión y la vigencia en su jurisdicción; las normas colombianas se incluyen como ejemplo de legislación local.
A4: GESTIÓN DEL RIESGO Y SISTEMAS DE GESTIÓN
A5: # | B5: Norma o estándar | C5: Qué aporta al checklist | D5: Dónde se aplica en este archivo
A6: 1 | B6: ISO 31000 | C6: Gestión del riesgo: principios y directrices. Base metodológica de la matriz (identificar, analizar, evaluar, tratar, monitorear). | D6: Toda la matriz
A7: 2 | B7: ISO 45001 / Decreto 1072 de 2015 | C7: Sistema de gestión de seguridad y salud en el trabajo. | D7: Riesgos de personas y SST
A8: 3 | B8: Resolución 0312 de 2019 (Colombia) | C8: Estándares mínimos del SG-SST y autoevaluación anual obligatoria. | D8: Cumplimiento legal SST
A9: 4 | B9: ISO 22301 | C9: Continuidad del negocio: BIA, RTO/RPO, estrategias y pruebas del plan. | D9: Continuidad y escenarios catastróficos
A10: 5 | B10: ISO 28000 / BASC / OEA / C-TPAT | C10: Seguridad de la cadena de suministro y protección de la carga. | D10: Seguridad física y exportación
A11: 6 | B11: ISO 27001 / NIST CSF | C11: Seguridad de la información y ciberseguridad. | D11: Riesgos de TI y del WMS
A13: ESTANTERÍA Y ALMACENAMIENTO
A14: # | B14: Norma o estándar | C14: Qué aporta al checklist | D14: Dónde se aplica en este archivo
A15: 1 | B15: EN 15635 | C15: Uso y mantenimiento del equipo de almacenamiento. Define el PRRS, la inspección visual periódica, la inspección experta anual y la clasificación de daños verde / ámbar / rojo. | D15: Todo el bloque B de la matriz
A16: 2 | B16: EN 15512 | C16: Diseño estructural de estanterías de paletización ajustable. | D16: Capacidad de carga y deflexión
A17: 3 | B17: EN 15629 | C17: Especificación del equipo de almacenamiento (montaje e instalación). | D17: Montaje y modificaciones
A18: 4 | B18: EN 15620 | C18: Tolerancias, deformaciones y holguras; requisitos de planitud del piso. | D18: Piso industrial y verticalidad
A19: 5 | B19: RMI ANSI MH16.1 (EE. UU.) | C19: Diseño, prueba y uso de estanterías industriales, incluido el diseño sísmico. | D19: Diseño y anclaje sísmico
A20: 6 | B20: FEM 10.2.08 | C20: Diseño sísmico de sistemas de almacenamiento en estanterías. | D20: Riesgo de sismo en racks
A22: PROTECCIÓN CONTRA INCENDIO
A23: # | B23: Norma o estándar | C23: Qué aporta al checklist | D23: Dónde se aplica en este archivo
A24: 1 | B24: NFPA 13 | C24: Instalación de sistemas de rociadores. Clasificación de mercancía, altura de almacenamiento y distancia libre bajo el rociador. | D24: Diseño de la protección
A25: 2 | B25: NFPA 25 | C25: Inspección, prueba y mantenimiento de sistemas de protección contra incendio a base de agua. Es la fuente de las frecuencias semanal, mensual, trimestral, anual y quinquenal. | D25: Frecuencias de la hoja de inspección
A26: 3 | B26: NFPA 10 / NTC 2885 | C26: Extintores portátiles: ubicación, inspección mensual, mantenimiento anual y prueba hidrostática. | D26: Extintores
A27: 4 | B27: NFPA 72 | C27: Sistemas de detección y alarma de incendio. | D27: Detección y notificación
A28: 5 | B28: NFPA 30 / 30B | C28: Líquidos inflamables y combustibles; productos en aerosol. | D28: Almacenamiento de inflamables
A29: 6 | B29: NFPA 51B | C29: Prevención de incendios en trabajos en caliente (permiso y vigía de fuego). | D29: Contratistas y mantenimiento
A30: 7 | B30: NFPA 80 / NFPA 221 | C30: Puertas cortafuego y muros cortafuego: sectorización. | D30: Compartimentación
A31: 8 | B31: NFPA 101 / NTC 1700 | C31: Seguridad humana: salidas, rutas de evacuación, señalización e iluminación de emergencia. | D31: Evacuación
A32: 9 | B32: NFPA 230 | C32: Protección contra incendio en almacenamiento (incluye estibas y almacenamiento en bloque). | D32: Carga de fuego
A33: 10 | B33: NFPA 855 | C33: Sistemas de almacenamiento de energía: baterías de ion-litio. | D33: Zona de carga de baterías
A34: 11 | B34: NFPA 110 / NFPA 20 | C34: Sistemas de energía de emergencia y bombas contra incendio. | D34: Respaldo y bombeo
A35: 12 | B35: FM Global Data Sheets (1-54, 8-24, entre otras) | C35: Guías de la aseguradora sobre drenaje de cubierta y almacenamiento de estibas. | D35: Requisitos de aseguradoras
A37: EQUIPOS DE MANIPULACIÓN Y SST
A38: # | B38: Norma o estándar | C38: Qué aporta al checklist | D38: Dónde se aplica en este archivo
A39: 1 | B39: OSHA 1910.178 | C39: Montacargas: inspección preoperacional por turno, certificación del operador y recertificación cada 3 años, aseguramiento de camiones en muelle. | D39: Bloque E de la matriz
A40: 2 | B40: ANSI/ITSDF B56.1 | C40: Requisitos de seguridad para equipos industriales motorizados. | D40: Operación de MHE
A41: 3 | B41: ISO 5057 | C41: Inspección y reparación de horquillas en servicio (desgaste máximo del 10%). | D41: Mantenimiento de MHE
A42: 4 | B42: Resolución 1409 de 2012 (Colombia) | C42: Trabajo en alturas: permisos, certificación, puntos de anclaje y EPP. | D42: Alturas, orderpicker y mezanine
A43: 5 | B43: ISO 11228 / ecuación NIOSH / REBA | C43: Manipulación manual de cargas y evaluación ergonómica. | D43: Riesgo ergonómico en picking
A44: 6 | B44: Resolución 2400 de 1979 (Colombia) | C44: Disposiciones sobre vivienda, higiene y seguridad en establecimientos de trabajo. | D44: Condiciones locativas e higiene
A45: 7 | B45: ANSI Z358.1 | C45: Duchas de emergencia y lavaojos. | D45: Sala de baterías y químicos
A47: INSTALACIONES, PRODUCTO Y ENTORNO
A48: # | B48: Norma o estándar | C48: Qué aporta al checklist | D48: Dónde se aplica en este archivo
A49: 1 | B49: NSR-10 (Colombia) / ASCE 7 / IBC | C49: Norma de construcción sismo resistente: diseño estructural, cargas de cubierta y amenaza sísmica. | D49: Estructura y sismo
A50: 2 | B50: RETIE / RETILAP / NTC 4552 | C50: Reglamentos de instalaciones eléctricas, iluminación y protección contra rayos. | D50: Riesgo eléctrico e iluminación
A51: 3 | B51: NFPA 70B / NETA | C51: Mantenimiento eléctrico preventivo y termografía. | D51: Tableros y subestación
A52: 4 | B52: Resolución 2674 de 2013 (Colombia) / HACCP / BPM | C52: Buenas prácticas de manufactura y condiciones sanitarias de almacenamiento de alimentos. | D52: Producto, plagas y humedad
A53: 5 | B53: Decreto 1609 de 2002 / NTC 1692 / SGA-GHS | C53: Transporte, rotulado y manejo de mercancías peligrosas. | D53: MERPEL
A54: 6 | B54: Decreto 4741 de 2005 / ISO 14001 | C54: Gestión de residuos peligrosos y sistema de gestión ambiental. | D54: Residuos y derrames
A55: 7 | B55: ISO 17712 | C55: Sellos de alta seguridad para contenedores. | D55: Trazabilidad de sellos
A56: 8 | B56: IIAR / ASHRAE 15 | C56: Seguridad en sistemas de refrigeración por amoníaco. | D56: Cuartos fríos industriales
